{"deployments": {"deployment0001": {"comparison": {"recovered_inst-ctdmo_ghqr_instrument_recovered telemetered-ctdmo_ghqr_sio_mule_instrument": {"vars": {"Seawater Density": {"ds0": {"name": "density", "units": "kg m-3", "n": 28371, "n_nan": 0, "missing": "no missing data"}, "ds1": {"name": "density", "units": "kg m-3", "n": 555, "n_nan": 0, "missing": "method not checked for missing data"}, "unit_test": "pass", "n_comparison": 555, "n_diff_greater_zero": 0, "min_abs_diff": 9.43e-08, "max_abs_diff": 0.0002033856}, "Practical Salinity": {"ds0": {"name": "practical_salinity", "units": "1", "n": 28371, "n_nan": 0, "missing": "no missing data"}, "ds1": {"name": "practical_salinity", "units": "1", "n": 555, "n_nan": 0, "missing": "method not checked for missing data"}, "unit_test": "pass", "n_comparison": 555, "n_diff_greater_zero": 0, "min_abs_diff": 2.214e-07, "max_abs_diff": 0.000142243}, "Seawater Pressure": {"ds0": {"name": "ctdmo_seawater_pressure", "units": "dbar", "n": 28371, "n_nan": 0, "missing": "no missing data"}, "ds1": {"name": "ctdmo_seawater_pressure", "units": "dbar", "n": 555, "n_nan": 0, "missing": "method not checked for missing data"}, "unit_test": "pass", "n_comparison": 555, "n_diff_greater_zero": 0, "min_abs_diff": 0.0027687853, "max_abs_diff": 0.0204184406}, "Seawater Temperature": {"ds0": {"name": "ctdmo_seawater_temperature", "units": "\u00baC", "n": 28371, "n_nan": 0, "missing": "no missing data"}, "ds1": {"name": "ctdmo_seawater_temperature", "units": "\u00baC", "n": 555, "n_nan": 0, "missing": "method not checked for missing data"}, "unit_test": "pass", "n_comparison": 555, "n_diff_greater_zero": 0, "min_abs_diff": 1.01e-08, "max_abs_diff": 0.0001011944}, "Seawater Conductivity": {"ds0": {"name": "ctdmo_seawater_conductivity", "units": "S m-1", "n": 28371, "n_nan": 0, "missing": "no missing data"}, "ds1": {"name": "ctdmo_seawater_conductivity", "units": "S m-1", "n": 555, "n_nan": 0, "missing": "method not checked for missing data"}, "unit_test": "pass", "n_comparison": 555, "n_diff_greater_zero": 0, "min_abs_diff": 4.4e-09, "max_abs_diff": 5.5479e-06}}}}}, "deployment0002": {"comparison": {"recovered_inst-ctdmo_ghqr_instrument_recovered recovered_host-ctdmo_ghqr_sio_mule_instrument": {"vars": {"Seawater Density": {"ds0": {"name": "density", "units": "kg m-3", "n": 34040, "n_nan": 0, "missing": "no missing data"}, "ds1": {"name": "density", "units": "kg m-3", "n": 33986, "n_nan": 0, "missing": {"missing_data_gaps": [["2016-12-05T20:15:01", "2016-12-06T09:30:01"]], "n_missing": [54], "n_missing_total": 54, "n_missing_days_total": 2}}, "unit_test": "pass", "n_comparison": 33986, "n_diff_greater_zero": 0, "min_abs_diff": 6.2e-09, "max_abs_diff": 0.0002018788}, "Practical Salinity": {"ds0": {"name": "practical_salinity", "units": "1", "n": 34040, "n_nan": 0, "missing": "no missing data"}, "ds1": {"name": "practical_salinity", "units": "1", "n": 33986, "n_nan": 0, "missing": {"missing_data_gaps": [["2016-12-05T20:15:01", "2016-12-06T09:30:01"]], "n_missing": [54], "n_missing_total": 54, "n_missing_days_total": 2}}, "unit_test": "pass", "n_comparison": 33986, "n_diff_greater_zero": 0, "min_abs_diff": 0.0, "max_abs_diff": 0.0001436597}, "Seawater Pressure": {"ds0": {"name": "ctdmo_seawater_pressure", "units": "dbar", "n": 34040, "n_nan": 0, "missing": "no missing data"}, "ds1": {"name": "ctdmo_seawater_pressure", "units": "dbar", "n": 33986, "n_nan": 0, "missing": {"missing_data_gaps": [["2016-12-05T20:15:01", "2016-12-06T09:30:01"]], "n_missing": [54], "n_missing_total": 54, "n_missing_days_total": 2}}, "unit_test": "pass", "n_comparison": 33986, "n_diff_greater_zero": 0, "min_abs_diff": 0.0028411411, "max_abs_diff": 0.0206228663}, "Seawater Temperature": {"ds0": {"name": "ctdmo_seawater_temperature", "units": "\u00baC", "n": 34040, "n_nan": 0, "missing": "no missing data"}, "ds1": {"name": "ctdmo_seawater_temperature", "units": "\u00baC", "n": 33986, "n_nan": 0, "missing": {"missing_data_gaps": [["2016-12-05T20:15:01", "2016-12-06T09:30:01"]], "n_missing": [54], "n_missing_total": 54, "n_missing_days_total": 2}}, "unit_test": "pass", "n_comparison": 33986, "n_diff_greater_zero": 0, "min_abs_diff": 2e-10, "max_abs_diff": 9.3492e-05}, "Seawater Conductivity": {"ds0": {"name": "ctdmo_seawater_conductivity", "units": "S m-1", "n": 34040, "n_nan": 0, "missing": "no missing data"}, "ds1": {"name": "ctdmo_seawater_conductivity", "units": "S m-1", "n": 33986, "n_nan": 0, "missing": {"missing_data_gaps": [["2016-12-05T20:15:01", "2016-12-06T09:30:01"]], "n_missing": [54], "n_missing_total": 54, "n_missing_days_total": 2}}, "unit_test": "pass", "n_comparison": 33986, "n_diff_greater_zero": 0, "min_abs_diff": 1e-10, "max_abs_diff": 6.5904e-06}}}, "recovered_inst-ctdmo_ghqr_instrument_recovered telemetered-ctdmo_ghqr_sio_mule_instrument": {"vars": {"Seawater Density": {"ds0": {"name": "density", "units": "kg m-3", "n": 34040, "n_nan": 0, "missing": "no missing data"}, "ds1": {"name": "density", "units": "kg m-3", "n": 277, "n_nan": 0, "missing": "method not checked for missing data"}, "unit_test": "pass", "n_comparison": 277, "n_diff_greater_zero": 0, "min_abs_diff": 2.081e-07, "max_abs_diff": 0.0001720308}, "Practical Salinity": {"ds0": {"name": "practical_salinity", "units": "1", "n": 34040, "n_nan": 0, "missing": "no missing data"}, "ds1": {"name": "practical_salinity", "units": "1", "n": 277, "n_nan": 0, "missing": "method not checked for missing data"}, "unit_test": "pass", "n_comparison": 277, "n_diff_greater_zero": 0, "min_abs_diff": 5.12e-08, "max_abs_diff": 0.0001137065}, "Seawater Pressure": {"ds0": {"name": "ctdmo_seawater_pressure", "units": "dbar", "n": 34040, "n_nan": 0, "missing": "no missing data"}, "ds1": {"name": "ctdmo_seawater_pressure", "units": "dbar", "n": 277, "n_nan": 0, "missing": "method not checked for missing data"}, "unit_test": "pass", "n_comparison": 277, "n_diff_greater_zero": 0, "min_abs_diff": 0.0029157613, "max_abs_diff": 0.020601271}, "Seawater Temperature": {"ds0": {"name": "ctdmo_seawater_temperature", "units": "\u00baC", "n": 34040, "n_nan": 0, "missing": "no missing data"}, "ds1": {"name": "ctdmo_seawater_temperature", "units": "\u00baC", "n": 277, "n_nan": 0, "missing": "method not checked for missing data"}, "unit_test": "pass", "n_comparison": 277, "n_diff_greater_zero": 0, "min_abs_diff": 2.917e-07, "max_abs_diff": 8.28921e-05}, "Seawater Conductivity": {"ds0": {"name": "ctdmo_seawater_conductivity", "units": "S m-1", "n": 34040, "n_nan": 0, "missing": "no missing data"}, "ds1": {"name": "ctdmo_seawater_conductivity", "units": "S m-1", "n": 277, "n_nan": 0, "missing": "method not checked for missing data"}, "unit_test": "pass", "n_comparison": 277, "n_diff_greater_zero": 0, "min_abs_diff": 1.33e-08, "max_abs_diff": 6.2412e-06}}}, "recovered_host-ctdmo_ghqr_sio_mule_instrument telemetered-ctdmo_ghqr_sio_mule_instrument": {"vars": {"Seawater Density": {"ds0": {"name": "density", "units": "kg m-3", "n": 33986, "n_nan": 0, "missing": "no missing data"}, "ds1": {"name": "density", "units": "kg m-3", "n": 277, "n_nan": 0, "missing": "method not checked for missing data"}, "unit_test": "pass", "n_comparison": 277, "n_diff_greater_zero": 0, "min_abs_diff": 0.0, "max_abs_diff": 0.0}, "Practical Salinity": {"ds0": {"name": "practical_salinity", "units": "1", "n": 33986, "n_nan": 0, "missing": "no missing data"}, "ds1": {"name": "practical_salinity", "units": "1", "n": 277, "n_nan": 0, "missing": "method not checked for missing data"}, "unit_test": "pass", "n_comparison": 277, "n_diff_greater_zero": 0, "min_abs_diff": 0.0, "max_abs_diff": 0.0}, "Seawater Pressure": {"ds0": {"name": "ctdmo_seawater_pressure", "units": "dbar", "n": 33986, "n_nan": 0, "missing": "no missing data"}, "ds1": {"name": "ctdmo_seawater_pressure", "units": "dbar", "n": 277, "n_nan": 0, "missing": "method not checked for missing data"}, "unit_test": "pass", "n_comparison": 277, "n_diff_greater_zero": 0, "min_abs_diff": 0.0, "max_abs_diff": 0.0}, "Seawater Temperature": {"ds0": {"name": "ctdmo_seawater_temperature", "units": "\u00baC", "n": 33986, "n_nan": 0, "missing": "no missing data"}, "ds1": {"name": "ctdmo_seawater_temperature", "units": "\u00baC", "n": 277, "n_nan": 0, "missing": "method not checked for missing data"}, "unit_test": "pass", "n_comparison": 277, "n_diff_greater_zero": 0, "min_abs_diff": 0.0, "max_abs_diff": 0.0}, "Seawater Conductivity": {"ds0": {"name": "ctdmo_seawater_conductivity", "units": "S m-1", "n": 33986, "n_nan": 0, "missing": "no missing data"}, "ds1": {"name": "ctdmo_seawater_conductivity", "units": "S m-1", "n": 277, "n_nan": 0, "missing": "method not checked for missing data"}, "unit_test": "pass", "n_comparison": 277, "n_diff_greater_zero": 0, "min_abs_diff": 0.0, "max_abs_diff": 0.0}}}}}}}