{"deployments": {"deployment0004": {"deploy_start": "2017-07-31T04:00:00+00:00", "deploy_stop": "2018-07-02T20:30:00+00:00", "n_days_deployed": 337, "lon": -129.753, "lat": 45.8305, "deploy_depth": null, "method": {"streamed": {"stream": {"velpt_velocity_data": {"file": {"deployment0004_RS03AXPS-SF03A-4B-VELPTD302-streamed-velpt_velocity_data": {"file_downloaded": "2019-12-02T15:52:43", "file_coordinates": ["obs", "time", "pressure_mbar", "lat", "lon"], "sampling_rate_seconds": 1, "sampling_rate_details": {"n_unique_rates": 31, "common_sampling_rates": {"0": "49.21%", "1": "50.79%"}}, "data_start": "2017-08-02T21:32:32", "data_stop": "2018-07-02T20:29:59", "time_gaps": [["2017-11-13T23:02:38", "2017-11-15T00:53:01"], ["2017-12-08T18:27:50", "2017-12-11T15:08:32"], ["2018-03-10T20:11:00", "2018-03-12T17:00:03"]], "unique_timestamps": "", "n_timestamps": 28276362, "n_days": 331, "notes": ["Pressure converted from 0.001 dbar to dbar for pressure comparison"], "ascending_timestamps": "not_tested", "pressure_comparison": {"pressure_mean": 128.73, "units": "0.001 dbar", "num_outliers": 0, "diff": null, "pressure_max": 195.07, "variable": "pressure_mbar", "pressure_compare": 195.07}, "vars_in_file": ["amplitude_beam1", "amplitude_beam2", "amplitude_beam3", "analog1", "battery_voltage_dv", "date_time_string", "driver_timestamp", "error_code", "heading_decidegree", "ingestion_timestamp", "internal_timestamp", "pitch_decidegree", "port_timestamp", "preferred_timestamp", "roll_decidegree", "sound_speed_dms", "status", "temperature_centidegree", "velocity_beam1", "velocity_beam2", "velocity_beam3", "velpt_d_eastward_velocity", "velpt_d_northward_velocity", "velpt_d_upward_velocity", "int_ctd_pressure", "time", "pressure_mbar"], "vars_not_in_file": [], "vars_not_in_db": ["int_ctd_pressure"], "sci_var_stats": {"pressure_mbar": {"n_outliers": 0, "mean": 128732.9623, "min": 3462.0, "max": 195067.0, "stdev": 59705.5787, "n_stats": 28276362, "units": ["0.001 dbar"], "n_nans": 0, "n_fillvalues": 0, "fill_value": "-9999999", "global_ranges": [0.0, 1100000.0], "n_grange": 0, "n_all": 28276362}, "velocity_beam1": {"n_outliers": 47200, "mean": 10.3067, "min": -1179.0, "max": 1201.0, "stdev": 231.5098, "n_stats": 28229162, "units": ["mm s-1"], "n_nans": 0, "n_fillvalues": 0, "fill_value": "-9999", "global_ranges": [-3000.0, 3000.0], "n_grange": 0, "n_all": 28276362}, "velocity_beam2": {"n_outliers": 51689, "mean": 15.1717, "min": -1187.0, "max": 1218.0, "stdev": 233.2672, "n_stats": 28224673, "units": ["mm s-1"], "n_nans": 0, "n_fillvalues": 0, "fill_value": "-9999", "global_ranges": [-3000.0, 3000.0], "n_grange": 0, "n_all": 28276362}, "velocity_beam3": {"n_outliers": 3845, "mean": -6.817, "min": -975.0, "max": 961.0, "stdev": 193.371, "n_stats": 28259915, "units": ["mm s-1"], "n_nans": 0, "n_fillvalues": 0, "fill_value": "-9999", "global_ranges": [-1000.0, 1000.0], "n_grange": 12602, "n_all": 28276362}, "velpt_d_eastward_velocity": {"n_outliers": 45819, "mean": 0.0143, "min": -1.1804, "max": 1.211, "stdev": 0.2328, "n_stats": 28230543, "units": ["m s-1"], "n_nans": 0, "n_fillvalues": 0, "fill_value": "-9999999.0", "global_ranges": [-3.0, 3.0], "n_grange": 0, "n_all": 28276362}, "velpt_d_northward_velocity": {"n_outliers": 49956, "mean": 0.0117, "min": -1.1857, "max": 1.2095, "stdev": 0.2325, "n_stats": 28226406, "units": ["m s-1"], "n_nans": 0, "n_fillvalues": 0, "fill_value": "-9999999.0", "global_ranges": [-3.0, 3.0], "n_grange": 0, "n_all": 28276362}, "velpt_d_upward_velocity": {"n_outliers": 3845, "mean": -0.0068, "min": -0.975, "max": 0.961, "stdev": 0.1934, "n_stats": 28259915, "units": ["m s-1"], "n_nans": 0, "n_fillvalues": 0, "fill_value": "-9999999.0", "global_ranges": [-1.0, 1.0], "n_grange": 12602, "n_all": 28276362}}}}}}}}}}, "location_comparison": {"diff_km_D2_to_D1": 0.0, "diff_km_D4_to_D1": 0.0, "diff_km_D4_to_D2": 0.0, "diff_km_D5_to_D1": 0.0, "diff_km_D5_to_D2": 0.0, "diff_km_D5_to_D4": 0.0}, "refdes": "RS03AXPS-SF03A-4B-VELPTD302"}