{"deployments": {"deployment0002": {"deploy_start": "2015-05-09T00:57:00", "deploy_stop": "2015-10-21T18:50:00", "n_days_deployed": 166, "lon": -70.8853, "lat": 40.3595, "deploy_depth": 97, "method": {"recovered_host": {"stream": {"phsen_abcdef_dcl_instrument_recovered": {"file": {"deployment0002_CP03ISSM-MFD35-06-PHSEND000-recovered_host-phsen_abcdef_dcl_instrument_recovered_20150509T010459-20150820T210459": {"file_downloaded": "2019-01-14T15:32:04", "file_coordinates": ["obs", "time", "lat", "lon"], "sampling_rate_seconds": 3600, "sampling_rate_details": {"n_unique_rates": 4, "common_sampling_rates": {"3600": "97.44%"}}, "data_start": "2015-05-09T01:04:59", "data_stop": "2015-08-20T21:04:59", "time_gaps": [], "unique_timestamps": "pass", "n_timestamps": 2423, "n_days": 104, "notes": [], "ascending_timestamps": "pass", "pressure_comparison": {"pressure_mean": null, "units": null, "num_outliers": null, "diff": null, "pressure_max": null, "variable": "no seawater pressure in file", "pressure_compare": null}, "vars_in_file": ["dcl_controller_timestamp", "driver_timestamp", "ingestion_timestamp", "internal_timestamp", "light_measurements", "passed_checksum", "port_timestamp", "preferred_timestamp", "record_time", "record_type", "reference_light_measurements", "thermistor_end", "thermistor_start", "unique_id", "voltage_battery", "phsen_thermistor_temperature", "phsen_abcdef_signal_intensity_434", "phsen_abcdef_signal_intensity_578", "practical_salinity", "phsen_abcdef_ph_seawater", "time"], "vars_not_in_file": [], "vars_not_in_db": ["practical_salinity"], "sci_var_stats": {"phsen_thermistor_temperature": {"n_outliers": 10, "mean": 12.424, "min": 7.8024, "max": 13.5828, "stdev": 0.8751, "n_stats": 2413, "units": "V", "n_nans": 0, "n_fillvalues": 0, "fill_value": "-9999999.0", "global_ranges": [null, null], "n_grange": "no global ranges"}, "phsen_abcdef_ph_seawater": {"n_outliers": 0, "mean": 7.6984, "min": 7.3093, "max": 8.4801, "stdev": 0.2654, "n_stats": 126, "units": "1", "n_nans": 0, "n_fillvalues": 2214, "fill_value": "-9999999.0", "global_ranges": [7.3, 8.5], "n_grange": 83}}}}}}}, "recovered_inst": {"stream": {"phsen_abcdef_instrument": {"file": {"deployment0002_CP03ISSM-MFD35-06-PHSEND000-recovered_inst-phsen_abcdef_instrument_20150509T010459-20151021T180459": {"file_downloaded": "2019-01-14T15:32:15", "file_coordinates": ["obs", "time", "lat", "lon"], "sampling_rate_seconds": 3600, "sampling_rate_details": {"n_unique_rates": 1, "common_sampling_rates": {"3600": "100.00%"}}, "data_start": "2015-05-09T01:04:59", "data_stop": "2015-10-21T18:04:59", "time_gaps": [], "unique_timestamps": "pass", "n_timestamps": 3978, "n_days": 166, "notes": [], "ascending_timestamps": "pass", "pressure_comparison": {"pressure_mean": null, "units": null, "num_outliers": null, "diff": null, "pressure_max": null, "variable": "no seawater pressure in file", "pressure_compare": null}, "vars_in_file": ["driver_timestamp", "ingestion_timestamp", "internal_timestamp", "light_measurements", "port_timestamp", "preferred_timestamp", "record_time", "record_type", "reference_light_measurements", "thermistor_end", "thermistor_start", "voltage_battery", "phsen_thermistor_temperature", "practical_salinity", "phsen_abcdef_ph_seawater", "time"], "vars_not_in_file": [], "vars_not_in_db": ["practical_salinity"], "sci_var_stats": {"phsen_thermistor_temperature": {"n_outliers": 16, "mean": 12.6601, "min": 9.312, "max": 14.8646, "stdev": 0.7758, "n_stats": 3962, "units": "V", "n_nans": 0, "n_fillvalues": 0, "fill_value": "-9999999.0", "global_ranges": [null, null], "n_grange": "no global ranges"}, "phsen_abcdef_ph_seawater": {"n_outliers": 0, "mean": 7.7409, "min": 7.3004, "max": 8.4924, "stdev": 0.2601, "n_stats": 3123, "units": "1", "n_nans": 0, "n_fillvalues": 0, "fill_value": "-9999999.0", "global_ranges": [7.3, 8.5], "n_grange": 855}}}}}}}, "telemetered": {"stream": {"phsen_abcdef_dcl_instrument": {"file": {"deployment0002_CP03ISSM-MFD35-06-PHSEND000-telemetered-phsen_abcdef_dcl_instrument_20150509T010459-20150820T170459": {"file_downloaded": "2019-01-14T15:32:27", "file_coordinates": ["obs", "time", "lat", "lon"], "sampling_rate_seconds": 3600, "sampling_rate_details": {"n_unique_rates": 4, "common_sampling_rates": {"3600": "97.44%"}}, "data_start": "2015-05-09T01:04:59", "data_stop": "2015-08-20T17:04:59", "time_gaps": [], "unique_timestamps": "pass", "n_timestamps": 2419, "n_days": 104, "notes": [], "ascending_timestamps": "pass", "pressure_comparison": {"pressure_mean": null, "units": null, "num_outliers": null, "diff": null, "pressure_max": null, "variable": "no seawater pressure in file", "pressure_compare": null}, "vars_in_file": ["dcl_controller_timestamp", "driver_timestamp", "ingestion_timestamp", "internal_timestamp", "light_measurements", "passed_checksum", "port_timestamp", "preferred_timestamp", "record_time", "record_type", "reference_light_measurements", "thermistor_end", "thermistor_start", "unique_id", "voltage_battery", "phsen_thermistor_temperature", "phsen_abcdef_signal_intensity_434", "phsen_abcdef_signal_intensity_578", "practical_salinity", "phsen_abcdef_ph_seawater", "time"], "vars_not_in_file": [], "vars_not_in_db": ["practical_salinity"], "sci_var_stats": {"phsen_thermistor_temperature": {"n_outliers": 10, "mean": 12.4231, "min": 7.8024, "max": 13.5828, "stdev": 0.8755, "n_stats": 2409, "units": "V", "n_nans": 0, "n_fillvalues": 0, "fill_value": "-9999999.0", "global_ranges": [null, null], "n_grange": "no global ranges"}, "phsen_abcdef_ph_seawater": {"n_outliers": 0, "mean": 7.6984, "min": 7.3093, "max": 8.4801, "stdev": 0.2654, "n_stats": 126, "units": "1", "n_nans": 0, "n_fillvalues": 2210, "fill_value": "-9999999.0", "global_ranges": [7.3, 8.5], "n_grange": 83}}}}}}}}}, "deployment0005": {"deploy_start": "2016-10-11T13:39:00", "deploy_stop": "2017-06-15T15:56:00", "n_days_deployed": 248, "lon": -70.8783, "lat": 40.3619, "deploy_depth": 92, "method": {"recovered_host": {"stream": {"phsen_abcdef_dcl_instrument_recovered": {"file": {"deployment0005_CP03ISSM-MFD35-06-PHSEND000-recovered_host-phsen_abcdef_dcl_instrument_recovered_20161011T135959-20170114T165959": {"file_downloaded": "2019-01-14T15:32:04", "file_coordinates": ["obs", "time", "lat", "lon"], "sampling_rate_seconds": 3600, "sampling_rate_details": {"n_unique_rates": 12, "common_sampling_rates": {"3600": "93.02%"}}, "data_start": "2016-10-11T13:59:59", "data_stop": "2017-01-14T16:59:59", "time_gaps": [["2017-01-01T20:59:59", "2017-01-03T06:59:59"], ["2017-01-03T16:59:59", "2017-01-05T00:59:59"], ["2017-01-05T18:59:59", "2017-01-08T00:59:59"], ["2017-01-08T06:59:59", "2017-01-10T00:59:59"], ["2017-01-10T00:59:59", "2017-01-14T16:59:59"]], "unique_timestamps": "pass", "n_timestamps": 1850, "n_days": 88, "notes": [], "ascending_timestamps": "pass", "pressure_comparison": {"pressure_mean": null, "units": null, "num_outliers": null, "diff": null, "pressure_max": null, "variable": "no seawater pressure in file", "pressure_compare": null}, "vars_in_file": ["dcl_controller_timestamp", "driver_timestamp", "ingestion_timestamp", "internal_timestamp", "light_measurements", "passed_checksum", "port_timestamp", "preferred_timestamp", "record_time", "record_type", "reference_light_measurements", "thermistor_end", "thermistor_start", "unique_id", "voltage_battery", "phsen_thermistor_temperature", "phsen_abcdef_signal_intensity_434", "phsen_abcdef_signal_intensity_578", "practical_salinity", "phsen_abcdef_ph_seawater", "time"], "vars_not_in_file": [], "vars_not_in_db": ["practical_salinity"], "sci_var_stats": {"phsen_thermistor_temperature": {"n_outliers": 0, "mean": 15.929, "min": 9.8687, "max": 19.5749, "stdev": 1.2183, "n_stats": 1850, "units": "V", "n_nans": 0, "n_fillvalues": 0, "fill_value": "-9999999.0", "global_ranges": [null, null], "n_grange": "no global ranges"}, "phsen_abcdef_ph_seawater": {"n_outliers": 1, "mean": 8.009, "min": 7.8602, "max": 8.1441, "stdev": 0.0384, "n_stats": 1849, "units": "1", "n_nans": 0, "n_fillvalues": 0, "fill_value": "-9999999.0", "global_ranges": [7.3, 8.5], "n_grange": 0}}}}}}}, "recovered_inst": {"stream": {"phsen_abcdef_instrument": {"file": {"deployment0005_CP03ISSM-MFD35-06-PHSEND000-recovered_inst-phsen_abcdef_instrument_20161011T135959-20170615T145959": {"file_downloaded": "2019-01-14T15:32:15", "file_coordinates": ["obs", "time", "lat", "lon"], "sampling_rate_seconds": 3600, "sampling_rate_details": {"n_unique_rates": 1, "common_sampling_rates": {"3600": "100.00%"}}, "data_start": "2016-10-11T13:59:59", "data_stop": "2017-06-15T14:59:59", "time_gaps": [], "unique_timestamps": "pass", "n_timestamps": 5930, "n_days": 248, "notes": [], "ascending_timestamps": "pass", "pressure_comparison": {"pressure_mean": null, "units": null, "num_outliers": null, "diff": null, "pressure_max": null, "variable": "no seawater pressure in file", "pressure_compare": null}, "vars_in_file": ["driver_timestamp", "ingestion_timestamp", "internal_timestamp", "light_measurements", "port_timestamp", "preferred_timestamp", "record_time", "record_type", "reference_light_measurements", "thermistor_end", "thermistor_start", "voltage_battery", "phsen_thermistor_temperature", "practical_salinity", "phsen_abcdef_ph_seawater", "time"], "vars_not_in_file": [], "vars_not_in_db": ["practical_salinity"], "sci_var_stats": {"phsen_thermistor_temperature": {"n_outliers": 0, "mean": 10.8343, "min": 4.4171, "max": 19.5749, "stdev": 4.3157, "n_stats": 5930, "units": "V", "n_nans": 0, "n_fillvalues": 0, "fill_value": "-9999999.0", "global_ranges": [null, null], "n_grange": "no global ranges"}, "phsen_abcdef_ph_seawater": {"n_outliers": 4, "mean": 8.0405, "min": 7.8602, "max": 8.2507, "stdev": 0.0424, "n_stats": 5925, "units": "1", "n_nans": 0, "n_fillvalues": 0, "fill_value": "-9999999.0", "global_ranges": [7.3, 8.5], "n_grange": 1}}}}}}}, "telemetered": {"stream": {"phsen_abcdef_dcl_instrument": {"file": {"deployment0005_CP03ISSM-MFD35-06-PHSEND000-telemetered-phsen_abcdef_dcl_instrument_20161011T135959-20170114T165959": {"file_downloaded": "2019-01-14T15:32:27", "file_coordinates": ["obs", "time", "lat", "lon"], "sampling_rate_seconds": 3600, "sampling_rate_details": {"n_unique_rates": 12, "common_sampling_rates": {"3600": "93.02%"}}, "data_start": "2016-10-11T13:59:59", "data_stop": "2017-01-14T16:59:59", "time_gaps": [["2017-01-01T20:59:59", "2017-01-03T06:59:59"], ["2017-01-03T16:59:59", "2017-01-05T00:59:59"], ["2017-01-05T18:59:59", "2017-01-08T00:59:59"], ["2017-01-08T06:59:59", "2017-01-10T00:59:59"], ["2017-01-10T00:59:59", "2017-01-14T16:59:59"]], "unique_timestamps": "pass", "n_timestamps": 1850, "n_days": 88, "notes": [], "ascending_timestamps": "pass", "pressure_comparison": {"pressure_mean": null, "units": null, "num_outliers": null, "diff": null, "pressure_max": null, "variable": "no seawater pressure in file", "pressure_compare": null}, "vars_in_file": ["dcl_controller_timestamp", "driver_timestamp", "ingestion_timestamp", "internal_timestamp", "light_measurements", "passed_checksum", "port_timestamp", "preferred_timestamp", "record_time", "record_type", "reference_light_measurements", "thermistor_end", "thermistor_start", "unique_id", "voltage_battery", "phsen_thermistor_temperature", "phsen_abcdef_signal_intensity_434", "phsen_abcdef_signal_intensity_578", "practical_salinity", "phsen_abcdef_ph_seawater", "time"], "vars_not_in_file": [], "vars_not_in_db": ["practical_salinity"], "sci_var_stats": {"phsen_thermistor_temperature": {"n_outliers": 0, "mean": 15.929, "min": 9.8687, "max": 19.5749, "stdev": 1.2183, "n_stats": 1850, "units": "V", "n_nans": 0, "n_fillvalues": 0, "fill_value": "-9999999.0", "global_ranges": [null, null], "n_grange": "no global ranges"}, "phsen_abcdef_ph_seawater": {"n_outliers": 1, "mean": 8.009, "min": 7.8602, "max": 8.1441, "stdev": 0.0384, "n_stats": 1849, "units": "1", "n_nans": 0, "n_fillvalues": 0, "fill_value": "-9999999.0", "global_ranges": [7.3, 8.5], "n_grange": 0}}}}}}}}}, "deployment0006": {"deploy_start": "2017-06-15T13:43:00", "deploy_stop": "2017-11-01T14:17:00", "n_days_deployed": 140, "lon": -70.8816, "lat": 40.3671, "deploy_depth": 93, "method": {"recovered_host": {"stream": {"phsen_abcdef_dcl_instrument_recovered": {"file": {"deployment0006_CP03ISSM-MFD35-06-PHSEND000-recovered_host-phsen_abcdef_dcl_instrument_recovered_20170615T185959-20171101T125959": {"file_downloaded": "2019-01-14T15:32:04", "file_coordinates": ["obs", "time", "lat", "lon"], "sampling_rate_seconds": 3600, "sampling_rate_details": {"n_unique_rates": 10, "common_sampling_rates": {"3600": "94.66%"}}, "data_start": "2017-06-15T18:59:59", "data_stop": "2017-11-01T12:59:59", "time_gaps": [["2017-08-16T13:59:59", "2017-08-30T15:59:59"], ["2017-10-06T13:59:59", "2017-11-01T12:59:59"]], "unique_timestamps": "pass", "n_timestamps": 2194, "n_days": 102, "notes": [], "ascending_timestamps": "pass", "pressure_comparison": {"pressure_mean": null, "units": null, "num_outliers": null, "diff": null, "pressure_max": null, "variable": "no seawater pressure in file", "pressure_compare": null}, "vars_in_file": ["dcl_controller_timestamp", "driver_timestamp", "ingestion_timestamp", "internal_timestamp", "light_measurements", "passed_checksum", "port_timestamp", "preferred_timestamp", "record_time", "record_type", "reference_light_measurements", "thermistor_end", "thermistor_start", "unique_id", "voltage_battery", "phsen_thermistor_temperature", "phsen_abcdef_signal_intensity_434", "phsen_abcdef_signal_intensity_578", "practical_salinity", "phsen_abcdef_ph_seawater", "time"], "vars_not_in_file": [], "vars_not_in_db": ["practical_salinity"], "sci_var_stats": {"phsen_thermistor_temperature": {"n_outliers": 0, "mean": 11.3484, "min": 7.6694, "max": 15.0258, "stdev": 1.7927, "n_stats": 2194, "units": "V", "n_nans": 0, "n_fillvalues": 0, "fill_value": "-9999999.0", "global_ranges": [null, null], "n_grange": "no global ranges"}, "phsen_abcdef_ph_seawater": {"n_outliers": 0, "mean": 7.9304, "min": 7.3108, "max": 8.4977, "stdev": 0.2489, "n_stats": 1102, "units": "1", "n_nans": 0, "n_fillvalues": 994, "fill_value": "-9999999.0", "global_ranges": [7.3, 8.5], "n_grange": 98}}}}}}}, "recovered_inst": {"stream": {"phsen_abcdef_instrument": {"file": {"deployment0006_CP03ISSM-MFD35-06-PHSEND000-recovered_inst-phsen_abcdef_instrument_20170615T185959-20171101T135959": {"file_downloaded": "2019-01-14T15:32:15", "file_coordinates": ["obs", "time", "lat", "lon"], "sampling_rate_seconds": 3600, "sampling_rate_details": {"n_unique_rates": 1, "common_sampling_rates": {"3600": "100.00%"}}, "data_start": "2017-06-15T18:59:59", "data_stop": "2017-11-01T13:59:59", "time_gaps": [], "unique_timestamps": "pass", "n_timestamps": 3332, "n_days": 140, "notes": [], "ascending_timestamps": "pass", "pressure_comparison": {"pressure_mean": null, "units": null, "num_outliers": null, "diff": null, "pressure_max": null, "variable": "no seawater pressure in file", "pressure_compare": null}, "vars_in_file": ["driver_timestamp", "ingestion_timestamp", "internal_timestamp", "light_measurements", "port_timestamp", "preferred_timestamp", "record_time", "record_type", "reference_light_measurements", "thermistor_end", "thermistor_start", "voltage_battery", "phsen_thermistor_temperature", "practical_salinity", "phsen_abcdef_ph_seawater", "time"], "vars_not_in_file": [], "vars_not_in_db": ["practical_salinity"], "sci_var_stats": {"phsen_thermistor_temperature": {"n_outliers": 0, "mean": 11.9858, "min": 7.6694, "max": 15.0489, "stdev": 1.8768, "n_stats": 3332, "units": "V", "n_nans": 0, "n_fillvalues": 0, "fill_value": "-9999999.0", "global_ranges": [null, null], "n_grange": "no global ranges"}, "phsen_abcdef_ph_seawater": {"n_outliers": 0, "mean": 7.9442, "min": 7.3046, "max": 8.495, "stdev": 0.2443, "n_stats": 1223, "units": "1", "n_nans": 0, "n_fillvalues": 2016, "fill_value": "-9999999.0", "global_ranges": [7.3, 8.5], "n_grange": 93}}}}}}}, "telemetered": {"stream": {"phsen_abcdef_dcl_instrument": {"file": {"deployment0006_CP03ISSM-MFD35-06-PHSEND000-telemetered-phsen_abcdef_dcl_instrument_20170615T185959-20171006T005959": {"file_downloaded": "2019-01-14T15:32:27", "file_coordinates": ["obs", "time", "lat", "lon"], "sampling_rate_seconds": 3600, "sampling_rate_details": {"n_unique_rates": 8, "common_sampling_rates": {"3600": "94.83%"}}, "data_start": "2017-06-15T18:59:59", "data_stop": "2017-10-06T00:59:59", "time_gaps": [["2017-08-16T13:59:59", "2017-08-30T15:59:59"]], "unique_timestamps": "pass", "n_timestamps": 2187, "n_days": 101, "notes": [], "ascending_timestamps": "pass", "pressure_comparison": {"pressure_mean": null, "units": null, "num_outliers": null, "diff": null, "pressure_max": null, "variable": "no seawater pressure in file", "pressure_compare": null}, "vars_in_file": ["dcl_controller_timestamp", "driver_timestamp", "ingestion_timestamp", "internal_timestamp", "light_measurements", "passed_checksum", "port_timestamp", "preferred_timestamp", "record_time", "record_type", "reference_light_measurements", "thermistor_end", "thermistor_start", "unique_id", "voltage_battery", "phsen_thermistor_temperature", "phsen_abcdef_signal_intensity_434", "phsen_abcdef_signal_intensity_578", "practical_salinity", "phsen_abcdef_ph_seawater", "time"], "vars_not_in_file": [], "vars_not_in_db": ["practical_salinity"], "sci_var_stats": {"phsen_thermistor_temperature": {"n_outliers": 0, "mean": 11.3407, "min": 7.6694, "max": 14.4053, "stdev": 1.7901, "n_stats": 2187, "units": "V", "n_nans": 0, "n_fillvalues": 0, "fill_value": "-9999999.0", "global_ranges": [null, null], "n_grange": "no global ranges"}, "phsen_abcdef_ph_seawater": {"n_outliers": 0, "mean": 7.9303, "min": 7.3108, "max": 8.4977, "stdev": 0.249, "n_stats": 1101, "units": "1", "n_nans": 0, "n_fillvalues": 988, "fill_value": "-9999999.0", "global_ranges": [7.3, 8.5], "n_grange": 98}}}}}}}}}, "deployment0007": {"deploy_start": "2017-11-01T12:22:00", "deploy_stop": "2018-03-28T16:56:00", "n_days_deployed": 148, "lon": -70.8855, "lat": 40.359, "deploy_depth": 93, "method": {"recovered_host": {"stream": {"phsen_abcdef_dcl_instrument_recovered": {"file": {"deployment0007_CP03ISSM-MFD35-06-PHSEND000-recovered_host-phsen_abcdef_dcl_instrument_recovered_20171102T005959-20171220T095959": {"file_downloaded": "2019-01-14T15:32:04", "file_coordinates": ["obs", "time", "lat", "lon"], "sampling_rate_seconds": 3600, "sampling_rate_details": {"n_unique_rates": 2, "common_sampling_rates": {"3600": "95.59%"}}, "data_start": "2017-11-02T00:59:59", "data_stop": "2017-12-20T09:59:59", "time_gaps": [], "unique_timestamps": "pass", "n_timestamps": 1113, "n_days": 49, "notes": [], "ascending_timestamps": "pass", "pressure_comparison": {"pressure_mean": null, "units": null, "num_outliers": null, "diff": null, "pressure_max": null, "variable": "no seawater pressure in file", "pressure_compare": null}, "vars_in_file": ["dcl_controller_timestamp", "driver_timestamp", "ingestion_timestamp", "internal_timestamp", "light_measurements", "passed_checksum", "port_timestamp", "preferred_timestamp", "record_time", "record_type", "reference_light_measurements", "thermistor_end", "thermistor_start", "unique_id", "voltage_battery", "phsen_thermistor_temperature", "phsen_abcdef_signal_intensity_434", "phsen_abcdef_signal_intensity_578", "practical_salinity", "phsen_abcdef_ph_seawater", "time"], "vars_not_in_file": [], "vars_not_in_db": ["practical_salinity"], "sci_var_stats": {"phsen_thermistor_temperature": {"n_outliers": 0, "mean": 14.4752, "min": 13.0146, "max": 15.4413, "stdev": 0.5434, "n_stats": 1113, "units": "V", "n_nans": 0, "n_fillvalues": 0, "fill_value": "-9999999.0", "global_ranges": [null, null], "n_grange": "no global ranges"}, "phsen_abcdef_ph_seawater": {"n_outliers": 1, "mean": 7.9729, "min": 7.8948, "max": 8.0547, "stdev": 0.0236, "n_stats": 1112, "units": "1", "n_nans": 0, "n_fillvalues": 0, "fill_value": "-9999999.0", "global_ranges": [7.3, 8.5], "n_grange": 0}}}}}}}, "recovered_inst": {"stream": {"phsen_abcdef_instrument": {"file": {"deployment0007_CP03ISSM-MFD35-06-PHSEND000-recovered_inst-phsen_abcdef_instrument_20171101T185959-20180328T155959": {"file_downloaded": "2019-01-14T15:32:15", "file_coordinates": ["obs", "time", "lat", "lon"], "sampling_rate_seconds": 3600, "sampling_rate_details": {"n_unique_rates": 1, "common_sampling_rates": {"3600": "100.00%"}}, "data_start": "2017-11-01T18:59:59", "data_stop": "2018-03-28T15:59:59", "time_gaps": [], "unique_timestamps": "pass", "n_timestamps": 3526, "n_days": 148, "notes": [], "ascending_timestamps": "pass", "pressure_comparison": {"pressure_mean": null, "units": null, "num_outliers": null, "diff": null, "pressure_max": null, "variable": "no seawater pressure in file", "pressure_compare": null}, "vars_in_file": ["driver_timestamp", "ingestion_timestamp", "internal_timestamp", "light_measurements", "port_timestamp", "preferred_timestamp", "record_time", "record_type", "reference_light_measurements", "thermistor_end", "thermistor_start", "voltage_battery", "phsen_thermistor_temperature", "practical_salinity", "phsen_abcdef_ph_seawater", "time"], "vars_not_in_file": [], "vars_not_in_db": ["practical_salinity"], "sci_var_stats": {"phsen_thermistor_temperature": {"n_outliers": 0, "mean": 11.9738, "min": 5.8108, "max": 15.4413, "stdev": 2.6523, "n_stats": 3526, "units": "V", "n_nans": 0, "n_fillvalues": 0, "fill_value": "-9999999.0", "global_ranges": [null, null], "n_grange": "no global ranges"}, "phsen_abcdef_ph_seawater": {"n_outliers": 5, "mean": 7.9972, "min": 7.8361, "max": 8.177, "stdev": 0.0367, "n_stats": 3521, "units": "1", "n_nans": 0, "n_fillvalues": 0, "fill_value": "-9999999.0", "global_ranges": [7.3, 8.5], "n_grange": 0}}}}}}}, "telemetered": {"stream": {"phsen_abcdef_dcl_instrument": {"file": {"deployment0007_CP03ISSM-MFD35-06-PHSEND000-telemetered-phsen_abcdef_dcl_instrument_20171101T185959-20171220T075959": {"file_downloaded": "2019-01-14T15:32:27", "file_coordinates": ["obs", "time", "lat", "lon"], "sampling_rate_seconds": 3600, "sampling_rate_details": {"n_unique_rates": 2, "common_sampling_rates": {"3600": "95.52%"}}, "data_start": "2017-11-01T18:59:59", "data_stop": "2017-12-20T07:59:59", "time_gaps": [], "unique_timestamps": "pass", "n_timestamps": 1116, "n_days": 50, "notes": [], "ascending_timestamps": "pass", "pressure_comparison": {"pressure_mean": null, "units": null, "num_outliers": null, "diff": null, "pressure_max": null, "variable": "no seawater pressure in file", "pressure_compare": null}, "vars_in_file": ["dcl_controller_timestamp", "driver_timestamp", "ingestion_timestamp", "internal_timestamp", "light_measurements", "passed_checksum", "port_timestamp", "preferred_timestamp", "record_time", "record_type", "reference_light_measurements", "thermistor_end", "thermistor_start", "unique_id", "voltage_battery", "phsen_thermistor_temperature", "phsen_abcdef_signal_intensity_434", "phsen_abcdef_signal_intensity_578", "practical_salinity", "phsen_abcdef_ph_seawater", "time"], "vars_not_in_file": [], "vars_not_in_db": ["practical_salinity"], "sci_var_stats": {"phsen_thermistor_temperature": {"n_outliers": 0, "mean": 14.4775, "min": 13.0146, "max": 15.4413, "stdev": 0.5438, "n_stats": 1116, "units": "V", "n_nans": 0, "n_fillvalues": 0, "fill_value": "-9999999.0", "global_ranges": [null, null], "n_grange": "no global ranges"}, "phsen_abcdef_ph_seawater": {"n_outliers": 1, "mean": 7.9728, "min": 7.8948, "max": 8.0547, "stdev": 0.0236, "n_stats": 1115, "units": "1", "n_nans": 0, "n_fillvalues": 0, "fill_value": "-9999999.0", "global_ranges": [7.3, 8.5], "n_grange": 0}}}}}}}}}, "deployment0003": {"deploy_start": "2015-10-21T17:44:00", "deploy_stop": "2016-05-14T13:45:00", "n_days_deployed": 207, "lon": -70.8884, "lat": 40.3647, "deploy_depth": 96, "method": {"recovered_inst": {"stream": {"phsen_abcdef_instrument": {"file": {"deployment0003_CP03ISSM-MFD35-06-PHSEND000-recovered_inst-phsen_abcdef_instrument_20151021T175959-20160413T155959": {"file_downloaded": "2019-01-14T15:32:15", "file_coordinates": ["obs", "time", "lat", "lon"], "sampling_rate_seconds": 3600, "sampling_rate_details": {"n_unique_rates": 1, "common_sampling_rates": {"3600": "100.00%"}}, "data_start": "2015-10-21T17:59:59", "data_stop": "2016-04-13T15:59:59", "time_gaps": [], "unique_timestamps": "pass", "n_timestamps": 4199, "n_days": 176, "notes": [], "ascending_timestamps": "pass", "pressure_comparison": {"pressure_mean": null, "units": null, "num_outliers": null, "diff": null, "pressure_max": null, "variable": "no seawater pressure in file", "pressure_compare": null}, "vars_in_file": ["driver_timestamp", "ingestion_timestamp", "internal_timestamp", "light_measurements", "port_timestamp", "preferred_timestamp", "record_time", "record_type", "reference_light_measurements", "thermistor_end", "thermistor_start", "voltage_battery", "phsen_thermistor_temperature", "practical_salinity", "phsen_abcdef_ph_seawater", "time"], "vars_not_in_file": [], "vars_not_in_db": ["practical_salinity"], "sci_var_stats": {"phsen_thermistor_temperature": {"n_outliers": 0, "mean": 14.1391, "min": 7.0938, "max": 18.3268, "stdev": 1.9082, "n_stats": 4199, "units": "V", "n_nans": 0, "n_fillvalues": 0, "fill_value": "-9999999.0", "global_ranges": [null, null], "n_grange": "no global ranges"}, "phsen_abcdef_ph_seawater": {"n_outliers": 0, "mean": 7.9672, "min": 7.3029, "max": 8.4996, "stdev": 0.2409, "n_stats": 3960, "units": "1", "n_nans": 2, "n_fillvalues": 0, "fill_value": "-9999999.0", "global_ranges": [7.3, 8.5], "n_grange": 237}}}}}}}}}, "deployment0004": {"deploy_start": "2016-05-28T14:43:00", "deploy_stop": "2016-10-15T12:14:00", "n_days_deployed": 141, "lon": -70.885, "lat": 40.3595, "deploy_depth": 95, "method": {"recovered_inst": {"stream": {"phsen_abcdef_instrument": {"file": {"deployment0004_CP03ISSM-MFD35-06-PHSEND000-recovered_inst-phsen_abcdef_instrument_20160528T220001-20161015T120000": {"file_downloaded": "2019-01-14T15:32:15", "file_coordinates": ["obs", "time", "lat", "lon"], "sampling_rate_seconds": 3600, "sampling_rate_details": {"n_unique_rates": 2, "common_sampling_rates": {"3600": "99.97%"}}, "data_start": "2016-05-28T22:00:01", "data_stop": "2016-10-15T12:00:00", "time_gaps": [], "unique_timestamps": "pass", "n_timestamps": 3351, "n_days": 141, "notes": [], "ascending_timestamps": "pass", "pressure_comparison": {"pressure_mean": null, "units": null, "num_outliers": null, "diff": null, "pressure_max": null, "variable": "no seawater pressure in file", "pressure_compare": null}, "vars_in_file": ["driver_timestamp", "ingestion_timestamp", "internal_timestamp", "light_measurements", "port_timestamp", "preferred_timestamp", "record_time", "record_type", "reference_light_measurements", "thermistor_end", "thermistor_start", "voltage_battery", "phsen_thermistor_temperature", "practical_salinity", "phsen_abcdef_ph_seawater", "time"], "vars_not_in_file": [], "vars_not_in_db": ["practical_salinity"], "sci_var_stats": {"phsen_thermistor_temperature": {"n_outliers": 0, "mean": 12.4523, "min": 9.3565, "max": 17.2846, "stdev": 1.3349, "n_stats": 3351, "units": "V", "n_nans": 0, "n_fillvalues": 0, "fill_value": "-9999999.0", "global_ranges": [null, null], "n_grange": "no global ranges"}, "phsen_abcdef_ph_seawater": {"n_outliers": 0, "mean": 7.9511, "min": 7.3015, "max": 8.4998, "stdev": 0.2501, "n_stats": 3085, "units": "1", "n_nans": 1, "n_fillvalues": 0, "fill_value": "-9999999.0", "global_ranges": [7.3, 8.5], "n_grange": 265}}}}}}}}}, "deployment0001": {"deploy_start": "2014-12-14T18:52:00", "deploy_stop": "2014-12-30T00:00:00", "n_days_deployed": 16, "lon": -70.8786, "lat": 40.3622, "deploy_depth": 94, "method": {"telemetered": {"stream": {"phsen_abcdef_dcl_instrument": {"file": {"deployment0001_CP03ISSM-MFD35-06-PHSEND000-telemetered-phsen_abcdef_dcl_instrument_20141214T190459-20141218T050459": {"file_downloaded": "2019-01-14T15:32:27", "file_coordinates": ["obs", "time", "lat", "lon"], "sampling_rate_seconds": 3600, "sampling_rate_details": {"n_unique_rates": 3, "common_sampling_rates": {"3600": "96.49%"}}, "data_start": "2014-12-14T19:04:59", "data_stop": "2014-12-18T05:04:59", "time_gaps": [["2014-12-14T23:04:59", "2014-12-16T00:04:59"]], "unique_timestamps": "pass", "n_timestamps": 58, "n_days": 4, "notes": [], "ascending_timestamps": "pass", "pressure_comparison": {"pressure_mean": null, "units": null, "num_outliers": null, "diff": null, "pressure_max": null, "variable": "no seawater pressure in file", "pressure_compare": null}, "vars_in_file": ["dcl_controller_timestamp", "driver_timestamp", "ingestion_timestamp", "internal_timestamp", "light_measurements", "passed_checksum", "port_timestamp", "preferred_timestamp", "record_time", "record_type", "reference_light_measurements", "thermistor_end", "thermistor_start", "unique_id", "voltage_battery", "phsen_thermistor_temperature", "phsen_abcdef_signal_intensity_434", "phsen_abcdef_signal_intensity_578", "practical_salinity", "phsen_abcdef_ph_seawater", "time"], "vars_not_in_file": [], "vars_not_in_db": ["practical_salinity"], "sci_var_stats": {"phsen_thermistor_temperature": {"n_outliers": 0, "mean": 16.1041, "min": 13.8336, "max": 16.5807, "stdev": 0.72, "n_stats": 58, "units": "V", "n_nans": 0, "n_fillvalues": 0, "fill_value": "-9999999.0", "global_ranges": [null, null], "n_grange": "no global ranges"}, "phsen_abcdef_ph_seawater": {"n_outliers": 0, "mean": 8.0271, "min": 7.973, "max": 8.0541, "stdev": 0.0207, "n_stats": 58, "units": "1", "n_nans": 0, "n_fillvalues": 0, "fill_value": "-9999999.0", "global_ranges": [7.3, 8.5], "n_grange": 0}}}}}}}}}}, "location_comparison": {"diff_km_D2_to_D1": 0.6433, "diff_km_D3_to_D1": 0.8775, "diff_km_D3_to_D2": 0.6346, "diff_km_D4_to_D1": 0.6208, "diff_km_D4_to_D2": 0.0255, "diff_km_D4_to_D3": 0.6456, "diff_km_D5_to_D1": 0.0419, "diff_km_D5_to_D2": 0.6516, "diff_km_D5_to_D3": 0.9125, "diff_km_D5_to_D4": 0.6284, "diff_km_D6_to_D1": 0.6008, "diff_km_D6_to_D2": 0.9005, "diff_km_D6_to_D3": 0.6361, "diff_km_D6_to_D4": 0.892, "diff_km_D6_to_D5": 0.6419, "diff_km_D7_to_D1": 0.6854, "diff_km_D7_to_D2": 0.0581, "diff_km_D7_to_D3": 0.6792, "diff_km_D7_to_D4": 0.0699, "diff_km_D7_to_D5": 0.6912, "diff_km_D7_to_D6": 0.9585, "diff_km_D8_to_D1": 0.6298, "diff_km_D8_to_D2": 0.8972, "diff_km_D8_to_D3": 0.6028, "diff_km_D8_to_D4": 0.8898, "diff_km_D8_to_D5": 0.6712, "diff_km_D8_to_D6": 0.0439, "diff_km_D8_to_D7": 0.9552, "diff_km_D9_to_D1": 0.6048, "diff_km_D9_to_D2": 0.9367, "diff_km_D9_to_D3": 0.684, "diff_km_D9_to_D4": 0.9273, "diff_km_D9_to_D5": 0.6451, "diff_km_D9_to_D6": 0.0479, "diff_km_D9_to_D7": 0.9945, "diff_km_D9_to_D8": 0.0857}, "refdes": "CP03ISSM-MFD35-06-PHSEND000"}