{"deployments": {"deployment0001": {"comparison": {"recovered_inst-ctdmo_ghqr_instrument_recovered telemetered-ctdmo_ghqr_sio_mule_instrument": {"vars": {"Seawater Density": {"ds0": {"name": "density", "units": "kg m-3", "n": 28371, "n_nan": 0, "missing": "no missing data"}, "ds1": {"name": "density", "units": "kg m-3", "n": 555, "n_nan": 0, "missing": "method not checked for missing data"}, "unit_test": "pass", "n_comparison": 555, "n_diff_greater_zero": 0, "min_abs_diff": 2.392e-07, "max_abs_diff": 0.0003579878}, "Practical Salinity": {"ds0": {"name": "practical_salinity", "units": "1", "n": 28371, "n_nan": 0, "missing": "no missing data"}, "ds1": {"name": "practical_salinity", "units": "1", "n": 555, "n_nan": 0, "missing": "method not checked for missing data"}, "unit_test": "pass", "n_comparison": 555, "n_diff_greater_zero": 0, "min_abs_diff": 1.77e-08, "max_abs_diff": 0.0001435688}, "Seawater Pressure": {"ds0": {"name": "ctdmo_seawater_pressure", "units": "dbar", "n": 28371, "n_nan": 0, "missing": "no missing data"}, "ds1": {"name": "ctdmo_seawater_pressure", "units": "dbar", "n": 555, "n_nan": 0, "missing": "method not checked for missing data"}, "unit_test": "pass", "n_comparison": 555, "n_diff_greater_zero": 0, "min_abs_diff": 0.0029690904, "max_abs_diff": 0.0654365118}, "Seawater Temperature": {"ds0": {"name": "ctdmo_seawater_temperature", "units": "\u00baC", "n": 28371, "n_nan": 0, "missing": "no missing data"}, "ds1": {"name": "ctdmo_seawater_temperature", "units": "\u00baC", "n": 555, "n_nan": 0, "missing": "method not checked for missing data"}, "unit_test": "pass", "n_comparison": 555, "n_diff_greater_zero": 0, "min_abs_diff": 1.681e-07, "max_abs_diff": 9.79461e-05}, "Seawater Conductivity": {"ds0": {"name": "ctdmo_seawater_conductivity", "units": "S m-1", "n": 28371, "n_nan": 0, "missing": "no missing data"}, "ds1": {"name": "ctdmo_seawater_conductivity", "units": "S m-1", "n": 555, "n_nan": 0, "missing": "method not checked for missing data"}, "unit_test": "pass", "n_comparison": 555, "n_diff_greater_zero": 0, "min_abs_diff": 2.9e-09, "max_abs_diff": 5.6213e-06}}}}}, "deployment0002": {"comparison": {"recovered_inst-ctdmo_ghqr_instrument_recovered recovered_host-ctdmo_ghqr_sio_mule_instrument": {"vars": {"Seawater Density": {"ds0": {"name": "density", "units": "kg m-3", "n": 34040, "n_nan": 0, "missing": "no missing data"}, "ds1": {"name": "density", "units": "kg m-3", "n": 33986, "n_nan": 0, "missing": {"missing_data_gaps": [["2016-12-05T20:15:01", "2016-12-06T09:30:01"]], "n_missing": [54], "n_missing_total": 54, "n_missing_days_total": 2}}, "unit_test": "pass", "n_comparison": 33986, "n_diff_greater_zero": 0, "min_abs_diff": 1.32e-08, "max_abs_diff": 0.0003782049}, "Practical Salinity": {"ds0": {"name": "practical_salinity", "units": "1", "n": 34040, "n_nan": 0, "missing": "no missing data"}, "ds1": {"name": "practical_salinity", "units": "1", "n": 33986, "n_nan": 0, "missing": {"missing_data_gaps": [["2016-12-05T20:15:01", "2016-12-06T09:30:01"]], "n_missing": [54], "n_missing_total": 54, "n_missing_days_total": 2}}, "unit_test": "pass", "n_comparison": 33986, "n_diff_greater_zero": 0, "min_abs_diff": 3.1e-09, "max_abs_diff": 0.000160177}, "Seawater Pressure": {"ds0": {"name": "ctdmo_seawater_pressure", "units": "dbar", "n": 34040, "n_nan": 0, "missing": "no missing data"}, "ds1": {"name": "ctdmo_seawater_pressure", "units": "dbar", "n": 33986, "n_nan": 0, "missing": {"missing_data_gaps": [["2016-12-05T20:15:01", "2016-12-06T09:30:01"]], "n_missing": [54], "n_missing_total": 54, "n_missing_days_total": 2}}, "unit_test": "pass", "n_comparison": 33986, "n_diff_greater_zero": 0, "min_abs_diff": 0.0021526315, "max_abs_diff": 0.0650060455}, "Seawater Temperature": {"ds0": {"name": "ctdmo_seawater_temperature", "units": "\u00baC", "n": 34040, "n_nan": 0, "missing": "no missing data"}, "ds1": {"name": "ctdmo_seawater_temperature", "units": "\u00baC", "n": 33986, "n_nan": 0, "missing": {"missing_data_gaps": [["2016-12-05T20:15:01", "2016-12-06T09:30:01"]], "n_missing": [54], "n_missing_total": 54, "n_missing_days_total": 2}}, "unit_test": "pass", "n_comparison": 33986, "n_diff_greater_zero": 0, "min_abs_diff": 1.29e-08, "max_abs_diff": 9.03349e-05}, "Seawater Conductivity": {"ds0": {"name": "ctdmo_seawater_conductivity", "units": "S m-1", "n": 34040, "n_nan": 0, "missing": "no missing data"}, "ds1": {"name": "ctdmo_seawater_conductivity", "units": "S m-1", "n": 33986, "n_nan": 0, "missing": {"missing_data_gaps": [["2016-12-05T20:15:01", "2016-12-06T09:30:01"]], "n_missing": [54], "n_missing_total": 54, "n_missing_days_total": 2}}, "unit_test": "pass", "n_comparison": 33986, "n_diff_greater_zero": 0, "min_abs_diff": 0.0, "max_abs_diff": 6.086e-06}}}, "recovered_inst-ctdmo_ghqr_instrument_recovered telemetered-ctdmo_ghqr_sio_mule_instrument": {"vars": {"Seawater Density": {"ds0": {"name": "density", "units": "kg m-3", "n": 34040, "n_nan": 0, "missing": "no missing data"}, "ds1": {"name": "density", "units": "kg m-3", "n": 277, "n_nan": 0, "missing": "method not checked for missing data"}, "unit_test": "pass", "n_comparison": 277, "n_diff_greater_zero": 0, "min_abs_diff": 5.563e-07, "max_abs_diff": 0.0003310435}, "Practical Salinity": {"ds0": {"name": "practical_salinity", "units": "1", "n": 34040, "n_nan": 0, "missing": "no missing data"}, "ds1": {"name": "practical_salinity", "units": "1", "n": 277, "n_nan": 0, "missing": "method not checked for missing data"}, "unit_test": "pass", "n_comparison": 277, "n_diff_greater_zero": 0, "min_abs_diff": 2.064e-07, "max_abs_diff": 0.0001469496}, "Seawater Pressure": {"ds0": {"name": "ctdmo_seawater_pressure", "units": "dbar", "n": 34040, "n_nan": 0, "missing": "no missing data"}, "ds1": {"name": "ctdmo_seawater_pressure", "units": "dbar", "n": 277, "n_nan": 0, "missing": "method not checked for missing data"}, "unit_test": "pass", "n_comparison": 277, "n_diff_greater_zero": 0, "min_abs_diff": 0.0022734196, "max_abs_diff": 0.0642095029}, "Seawater Temperature": {"ds0": {"name": "ctdmo_seawater_temperature", "units": "\u00baC", "n": 34040, "n_nan": 0, "missing": "no missing data"}, "ds1": {"name": "ctdmo_seawater_temperature", "units": "\u00baC", "n": 277, "n_nan": 0, "missing": "method not checked for missing data"}, "unit_test": "pass", "n_comparison": 277, "n_diff_greater_zero": 0, "min_abs_diff": 1.904e-07, "max_abs_diff": 7.63873e-05}, "Seawater Conductivity": {"ds0": {"name": "ctdmo_seawater_conductivity", "units": "S m-1", "n": 34040, "n_nan": 0, "missing": "no missing data"}, "ds1": {"name": "ctdmo_seawater_conductivity", "units": "S m-1", "n": 277, "n_nan": 0, "missing": "method not checked for missing data"}, "unit_test": "pass", "n_comparison": 277, "n_diff_greater_zero": 0, "min_abs_diff": 3.6e-09, "max_abs_diff": 5.5108e-06}}}, "recovered_host-ctdmo_ghqr_sio_mule_instrument telemetered-ctdmo_ghqr_sio_mule_instrument": {"vars": {"Seawater Density": {"ds0": {"name": "density", "units": "kg m-3", "n": 33986, "n_nan": 0, "missing": "no missing data"}, "ds1": {"name": "density", "units": "kg m-3", "n": 277, "n_nan": 0, "missing": "method not checked for missing data"}, "unit_test": "pass", "n_comparison": 277, "n_diff_greater_zero": 0, "min_abs_diff": 0.0, "max_abs_diff": 0.0}, "Practical Salinity": {"ds0": {"name": "practical_salinity", "units": "1", "n": 33986, "n_nan": 0, "missing": "no missing data"}, "ds1": {"name": "practical_salinity", "units": "1", "n": 277, "n_nan": 0, "missing": "method not checked for missing data"}, "unit_test": "pass", "n_comparison": 277, "n_diff_greater_zero": 0, "min_abs_diff": 0.0, "max_abs_diff": 0.0}, "Seawater Pressure": {"ds0": {"name": "ctdmo_seawater_pressure", "units": "dbar", "n": 33986, "n_nan": 0, "missing": "no missing data"}, "ds1": {"name": "ctdmo_seawater_pressure", "units": "dbar", "n": 277, "n_nan": 0, "missing": "method not checked for missing data"}, "unit_test": "pass", "n_comparison": 277, "n_diff_greater_zero": 0, "min_abs_diff": 0.0, "max_abs_diff": 0.0}, "Seawater Temperature": {"ds0": {"name": "ctdmo_seawater_temperature", "units": "\u00baC", "n": 33986, "n_nan": 0, "missing": "no missing data"}, "ds1": {"name": "ctdmo_seawater_temperature", "units": "\u00baC", "n": 277, "n_nan": 0, "missing": "method not checked for missing data"}, "unit_test": "pass", "n_comparison": 277, "n_diff_greater_zero": 0, "min_abs_diff": 0.0, "max_abs_diff": 0.0}, "Seawater Conductivity": {"ds0": {"name": "ctdmo_seawater_conductivity", "units": "S m-1", "n": 33986, "n_nan": 0, "missing": "no missing data"}, "ds1": {"name": "ctdmo_seawater_conductivity", "units": "S m-1", "n": 277, "n_nan": 0, "missing": "method not checked for missing data"}, "unit_test": "pass", "n_comparison": 277, "n_diff_greater_zero": 0, "min_abs_diff": 0.0, "max_abs_diff": 0.0}}}}}}}